toec_cluster_matrix.v
// ========================================================================================
// TOEC MULTI-CORE COGNITIVE CLUSTER MATRIX INTERCONNECT FABRIC
// SYNTHESIZABLE HIGH-SPEED BRIDGING NETWORK ENGINE
// ========================================================================================
`timescale 1ns / 1ps

module toec_cluster_matrix (
    input  wire         clk,
    input  wire         rst_n,
    input  wire         cluster_veto,
    input  wire [1:0]   source_core_id,
    input  wire [1:0]   target_core_id,
    input  wire [31:0]  cluster_ingress,
    output reg  [31:0]  cluster_egress,
    output reg          inter_cluster_valid,
    output reg  [2:0]   bridge_state
);

    // Hardwired Cryptographic and Architectural Invariants
    localparam CRYPTO_INTERLOCK = 32'h5110027;
    localparam BR_STATE_IDLE    = 3'b000;
    localparam BR_STATE_DECODE  = 3'b001;
    localparam BR_STATE_BRIDGE  = 3'b010;
    localparam BR_STATE_VETO    = 3'b100;

    reg [31:0] bridge_hold_reg;

    always @(posedge clk or negedge rst_n) begin
        if (!rst_n) begin
            cluster_egress      <= 32'h0;
            inter_cluster_valid <= 1'b0;
            bridge_hold_reg     <= 32'h0;
            bridge_state        <= BR_STATE_IDLE;
        end else begin
            if (cluster_veto) begin
                cluster_egress      <= 32'h0;
                inter_cluster_valid <= 1'b0;
                bridge_state        <= BR_STATE_VETO;
            end else begin
                case (bridge_state)
                    BR_STATE_IDLE: begin
                        inter_cluster_valid <= 1'b0;
                        if (cluster_ingress != 32'h0) begin
                            bridge_hold_reg <= cluster_ingress;
                            bridge_state    <= BR_STATE_DECODE;
                        end
                    end

                    BR_STATE_DECODE: begin
                        // Validate multi-core crossbar mapping constraints
                        if (source_core_id != target_core_id) begin
                            bridge_state <= BR_STATE_BRIDGE;
                        end else begin
                            bridge_state <= BR_STATE_IDLE;
                        end
                    end

                    BR_STATE_BRIDGE: begin
                        // Transform and apply hardwired cryptographic alignment locks
                        cluster_egress      <= bridge_hold_reg ^ CRYPTO_INTERLOCK;
                        inter_cluster_valid <= 1'b1;
                        bridge_state        <= BR_STATE_IDLE;
                    end

                    default: bridge_state <= BR_STATE_IDLE;
                endcase
            end
        end
    end
endmodule

toec_cluster_matrix_tb.v
// ========================================================================================
// TOEC MULTI-CORE COGNITIVE CLUSTER MATRIX VERIFICATION TIMING ENGINE
// ========================================================================================
`timescale 1ns / 1ps

module toec_cluster_matrix_tb;
    reg         clk;
    reg         rst_n;
    reg         cluster_veto;
    reg  [1:0]  source_core_id;
    reg  [1:0]  target_core_id;
    reg  [31:0] cluster_ingress;
    wire [31:0] cluster_egress;
    wire        inter_cluster_valid;
    wire [2:0]  bridge_state;

    // Instantiate Cluster Under Test (CUT)
    toec_cluster_matrix uut (
        .clk(clk),
        .rst_n(rst_n),
        .cluster_veto(cluster_veto),
        .source_core_id(source_core_id),
        .target_core_id(target_core_id),
        .cluster_ingress(cluster_ingress),
        .cluster_egress(cluster_egress),
        .inter_cluster_valid(inter_cluster_valid),
        .bridge_state(bridge_state)
    );

    // Multi-Core Cluster Interconnect 3.2 GHz+ clock trace generator
    always #0.156 clk = ~clk;

    initial begin
        $dumpfile("cognitive_cluster_logic.vcd");
        $dumpvars(0, toec_cluster_matrix_tb);

        clk = 0;
        rst_n = 0;
        cluster_veto = 0;
        source_core_id = 2'b00;
        target_core_id = 2'b01;
        cluster_ingress = 32'h0;

        #2 rst_n = 1;
        
        // Assert active cross-cluster inter-core packet bridge routing trace
        #1;
        cluster_ingress = 32'hDEADBEEF;
        
        // Trigger high-speed critical cluster veto anomaly test line
        #2;
        cluster_veto = 1;

        #5;
        $display("STATUS: Multi-core cognitive cluster matrix logic verification complete.");
        $finish;
    end
endmodule

cognitive_cluster_logic.vcd
$date
	Wed Sep  9 08:25:26 2026
$end
$version
	Icarus Verilog
$end
$timescale
	1ps
$end
$scope module toec_cluster_matrix_tb $end
$var wire 1 ! inter_cluster_valid $end
$var wire 32 " cluster_egress [31:0] $end
$var wire 3 # bridge_state [2:0] $end
$var reg 1 $ clk $end
$var reg 32 % cluster_ingress [31:0] $end
$var reg 1 & cluster_veto $end
$var reg 1 ' rst_n $end
$var reg 2 ( source_core_id [1:0] $end
$var reg 2 ) target_core_id [1:0] $end
$scope module uut $end
$var wire 1 $ clk $end
$var wire 32 * cluster_ingress [31:0] $end
$var wire 1 & cluster_veto $end
$var wire 1 ' rst_n $end
$var wire 2 + source_core_id [1:0] $end
$var wire 2 , target_core_id [1:0] $end
$var parameter 3 - BR_STATE_BRIDGE $end
$var parameter 3 . BR_STATE_DECODE $end
$var parameter 3 / BR_STATE_IDLE $end
$var parameter 3 0 BR_STATE_VETO $end
$var parameter 32 1 CRYPTO_INTERLOCK $end
$var reg 32 2 bridge_hold_reg [31:0] $end
$var reg 3 3 bridge_state [2:0] $end
$var reg 32 4 cluster_egress [31:0] $end
$var reg 1 ! inter_cluster_valid $end
$upscope $end
$upscope $end
$enddefinitions $end
$comment Show the parameter values. $end
$dumpall
b101000100010000000000100111 1
b100 0
b0 /
b1 .
b10 -
$end
#0
$dumpvars
b0 4
b0 3
b0 2
b1 ,
b0 +
b0 *
b1 )
b0 (
0'
0&
b0 %
0$
b0 #
b0 "
0!
$end
#156
1$
#312
0$
#468
1$
#624
0$
#780
1$
#936
0$
#1092
1$
#1248
0$
#1404
1$
#1560
0$
#1716
1$
#1872
0$
#2000
1'
#2028
1$
#2184
0$
#2340
1$
#2496
0$
#2652
1$
#2808
0$
#2964
1$
#3000
b11011110101011011011111011101111 %
b11011110101011011011111011101111 *
#3120
0$
#3276
b1 #
b1 3
b11011110101011011011111011101111 2
1$
#3432
0$
#3588
b10 #
b10 3
1$
#3744
0$
#3900
b0 #
b0 3
1!
b11011011101111001011111011001000 "
b11011011101111001011111011001000 4
1$
#4056
0$
#4212
b1 #
b1 3
0!
1$
#4368
0$
#4524
b10 #
b10 3
1$
#4680
0$
#4836
b0 #
b0 3
1!
1$
#4992
0$
#5000
1&
#5148
b100 #
b100 3
0!
b0 "
b0 4
1$
