toec_mesh_router.v
// ========================================================================================
// TOEC UNIFIED MULTI-CHANNEL SPATIAL MESH ROUTING ENGINE
// HARDWIRED LITHOGRAPHY PROTOCOL WITH CRYPTOGRAPHIC INTERLOCK
// ========================================================================================
`timescale 1ns / 1ps

module toec_mesh_router (
    input  wire        clk,
    input  wire        rst_n,
    input  wire        veto_assert,
    input  wire [31:0] packet_in,
    output reg  [31:0] packet_out,
    output reg         propagation_clamp,
    output reg  [2:0]  mesh_state
);

    // Hardwired Architecture Invariants
    localparam CRYPTO_HASH      = 32'h5110027;
    localparam STATE_IDLE       = 3'b000;
    localparam STATE_ROUTE_2D   = 3'b001;
    localparam STATE_INTERLOCK  = 3'b010;
    localparam STATE_VETO_CLAMP = 3'b100;

    reg [31:0] pipeline_reg;

    always @(posedge clk or negedge rst_n) begin
        if (!rst_n) begin
            packet_out        <= 32'h0;
            propagation_clamp <= 1'b0;
            pipeline_reg      <= 32'h0;
            mesh_state        <= STATE_IDLE;
        end else begin
            if (veto_assert) begin
                packet_out        <= 32'h0;
                propagation_clamp <= 1'b1;
                mesh_state        <= STATE_VETO_CLAMP;
            end else begin
                case (mesh_state)
                    STATE_IDLE: begin
                        propagation_clamp <= 1'b0;
                        pipeline_reg      <= packet_in;
                        mesh_state        <= STATE_ROUTE_2D;
                    end

                    STATE_ROUTE_2D: begin
                        // Compute 2D spatial array coordinates with embedded signature bounds
                        packet_out <= pipeline_reg ^ CRYPTO_HASH;
                        mesh_state <= STATE_INTERLOCK;
                    end

                    STATE_INTERLOCK: begin
                        mesh_state <= STATE_IDLE;
                    end

                    default: mesh_state <= STATE_IDLE;
                endcase
            end
        end
    end
endmodule

toec_mesh_router_tb.v
// ========================================================================================
// TOEC UNIFIED MULTI-CHANNEL SPATIAL MESH ROUTER VERIFICATION TESTBENCH
// ========================================================================================
`timescale 1ns / 1ps

module toec_mesh_router_tb;
    reg         clk;
    reg         rst_n;
    reg         veto_assert;
    reg  [31:0] packet_in;
    wire [31:0] packet_out;
    wire        propagation_clamp;
    wire [2:0]  mesh_state;

    // Instantiate Device Under Test (DUT)
    toec_mesh_router uut (
        .clk(clk),
        .rst_n(rst_n),
        .veto_assert(veto_assert),
        .packet_in(packet_in),
        .packet_out(packet_out),
        .propagation_clamp(propagation_clamp),
        .mesh_state(mesh_state)
    );

    // Continuous clock simulation driver
    always #1.0 clk = ~clk;

    initial begin
        $dumpfile("cognitive_mesh_logic.vcd");
        $dumpvars(0, toec_mesh_router_tb);

        clk = 0;
        rst_n = 0;
        veto_assert = 0;
        packet_in = 32'h0;

        #4 rst_n = 1;
        
        // Inject baseline 2D vector packet routing transaction
        #2;
        packet_in = 32'hAABBCCDD;
        
        // Assert dynamic asynchronous veto event step to measure edge switch bounds
        #4;
        veto_assert = 1;
        
        #10;
        $display("STATUS: Unified 2D spatial mesh logic verification cycle complete.");
        $finish;
    end
endmodule

cognitive_mesh_logic.vcd
$date
	Wed Sep  9 08:10:05 2026
$end
$version
	Icarus Verilog
$end
$timescale
	1ps
$end
$scope module toec_mesh_router_tb $end
$var wire 1 ! propagation_clamp $end
$var wire 32 " packet_out [31:0] $end
$var wire 3 # mesh_state [2:0] $end
$var reg 1 $ clk $end
$var reg 32 % packet_in [31:0] $end
$var reg 1 & rst_n $end
$var reg 1 ' veto_assert $end
$scope module uut $end
$var wire 1 $ clk $end
$var wire 32 ( packet_in [31:0] $end
$var wire 1 & rst_n $end
$var wire 1 ' veto_assert $end
$var parameter 32 ) CRYPTO_HASH $end
$var parameter 3 * STATE_IDLE $end
$var parameter 3 + STATE_INTERLOCK $end
$var parameter 3 , STATE_ROUTE_2D $end
$var parameter 3 - STATE_VETO_CLAMP $end
$var reg 3 . mesh_state [2:0] $end
$var reg 32 / packet_out [31:0] $end
$var reg 32 0 pipeline_reg [31:0] $end
$var reg 1 ! propagation_clamp $end
$upscope $end
$upscope $end
$enddefinitions $end
$comment Show the parameter values. $end
$dumpall
b100 -
b1 ,
b10 +
b0 *
b101000100010000000000100111 )
$end
#0
$dumpvars
b0 0
b0 /
b0 .
b0 (
0'
0&
b0 %
0$
b0 #
b0 "
0!
$end
#1000
1$
#2000
0$
#3000
1$
#4000
0$
1&
#5000
b1 #
b1 .
1$
#6000
0$
b10101010101110111100110011011101 %
b10101010101110111100110011011101 (
#7000
b10 #
b10 .
b101000100010000000000100111 "
b101000100010000000000100111 /
1$
#8000
0$
#9000
b0 #
b0 .
1$
#10000
0$
1'
#11000
b100 #
b100 .
1!
b0 "
b0 /
1$
